Hello_World_Package-0.1.3.dist-info/DESCRIPTION.rst
Hello_World_Package-0.1.3.dist-info/METADATA
Hello_World_Package-0.1.3.dist-info/RECORD
Hello_World_Package-0.1.3.dist-info/WHEEL
Hello_World_Package-0.1.3.dist-info/entry_points.txt
Hello_World_Package-0.1.3.dist-info/metadata.json
Hello_World_Package-0.1.3.dist-info/top_level.txt
hello_world/__init__.py
hello_world/_version.py
hello_world/cli.py
